fuzzylab/FuzzyInferenceSystem.py
fuzzylab/__init__.py
fuzzylab/arange.py
fuzzylab/defuzz.py
fuzzylab/evalfis.py
fuzzylab/evalmf.py
fuzzylab/fismf.py
fuzzylab/fisrule.py
fuzzylab/fisvar.py
fuzzylab/gaussmf.py
fuzzylab/gbellmf.py
fuzzylab/gensurf.py
fuzzylab/mamfis.py
fuzzylab/plotmf.py
fuzzylab/readfis.py
fuzzylab/sugfis.py
fuzzylab/trapmf.py
fuzzylab/trimf.py
fuzzylab/writefis.py
fuzzylab-0.13.dist-info/LICENSE
fuzzylab-0.13.dist-info/METADATA
fuzzylab-0.13.dist-info/WHEEL
fuzzylab-0.13.dist-info/top_level.txt
fuzzylab-0.13.dist-info/RECORD
