Metadata-Version: 2.1
Name: fuzzylab
Version: 0.13
Summary: Python Fuzzy Logic library
Home-page: https://github.com/ITTcs/fuzzylab
Author: Eduardo Avelar
Author-email: eavelardev@gmail.com
Classifier: Programming Language :: Python :: 3
Classifier: License :: OSI Approved :: MIT License
Classifier: Operating System :: OS Independent
License-File: LICENSE
